{"formationId":95,"criteria":{"minSamples":30,"minUniquePlayers":8,"candidatePool":{"nr":"active NR players","cc":"active CC players","ss":"players in latest two scout events","cm":"excluded","retired":"excluded"},"features":[{"key":"spd","label":"Speed"},{"key":"tec","label":"Technique"},{"key":"pwr","label":"Power"},{"key":"individual","label":"Individual"},{"key":"organization","label":"Organization"},{"key":"sense","label":"Sense"},{"key":"intelligence","label":"Intelligence"},{"key":"r1","label":"R1"},{"key":"r2","label":"R2"},{"key":"r3","label":"R3"},{"key":"r4","label":"R4"},{"key":"r5","label":"R5"},{"key":"r6","label":"R6"},{"key":"r7","label":"R7"},{"key":"r8","label":"R8"},{"key":"r9","label":"R9"},{"key":"r10","label":"R10"},{"key":"r11","label":"R11"},{"key":"r12","label":"R12"},{"key":"r13","label":"R13"},{"key":"r14","label":"R14"},{"key":"r15","label":"R15"},{"key":"r16","label":"R16"},{"key":"r17","label":"R17"},{"key":"r18","label":"R18"}],"method":"high-sample top performer profile similarity with category-effect adjustment"},"slots":{"1":{"status":"ok","sampleSize":38,"uniquePlayers":10,"confidence":"Low","method":"top_performer_profile_similarity","categoryEffects":{"CC":0.0,"SS":0.0,"CM":0.0563,"NR":-0.0563},"target":{"pwr":0.9087,"individual":0.6793,"sense":0.6749,"r3":0.1429,"r6":0.1429,"r8":0.1429,"r9":0.1429,"r10":0.1875,"r11":0.2321,"r12":0.1875,"r13":1.0,"r17":0.1429,"r18":0.3214},"corePattern":{"kind":"high_balanced","primary":"Technique","secondary":"Speed","gaps":[0.05,0.0047],"level":0.9285,"floor":0.9087},"referencePlayers":[{"playerId":3032,"playerName":"マリテレス","uses":1,"avgPts":4.0563},{"playerId":169,"playerName":"ブッチ","uses":6,"avgPts":3.2229},{"playerId":429,"playerName":"エルデラ","uses":8,"avgPts":3.0563},{"playerId":1019,"playerName":"ドグレル","uses":3,"avgPts":3.3896},{"playerId":456,"playerName":"プラーニチカ","uses":5,"avgPts":2.8563}],"requirements":[{"key":"sense","label":"Sense","weight":0.034538},{"key":"individual","label":"Individual","weight":0.03372},{"key":"r13","label":"R13","weight":0.022556},{"key":"pwr","label":"Power","weight":0.019204}],"top":[{"playerId":1042,"playerName":"シューマン","playerFullName":"ウェスト・シューマン","category":"NR","rate":7,"score":85.082,"bestSeason":"1期","params":{"spd":9,"tec":10,"pwr":9,"individual":19,"organization":19,"sense":23,"intelligence":24,"r1":1,"r2":1,"r3":1,"r4":1,"r5":1,"r6":1,"r7":1,"r8":1,"r9":1,"r10":1,"r11":1,"r12":1,"r13":7,"r14":7,"r15":7,"r16":1,"r17":1,"r18":1}},{"playerId":1019,"playerName":"ドグレル","playerFullName":"ティム・ドグレル","category":"NR","rate":6,"score":84.924,"bestSeason":"4期","params":{"spd":9,"tec":9,"pwr":10,"individual":18,"organization":23,"sense":17,"intelligence":23,"r1":1,"r2":1,"r3":1,"r4":1,"r5":1,"r6":1,"r7":1,"r8":1,"r9":1,"r10":1,"r11":1,"r12":1,"r13":7,"r14":7,"r15":7,"r16":1,"r17":1,"r18":1}},{"playerId":456,"playerName":"プラーニチカ","playerFullName":"パベル・プラーニチカ","category":"NR","rate":6,"score":83.939,"bestSeason":"1期","params":{"spd":9,"tec":9,"pwr":9,"individual":17,"organization":23,"sense":16,"intelligence":23,"r1":1,"r2":1,"r3":1,"r4":1,"r5":1,"r6":1,"r7":1,"r8":1,"r9":1,"r10":1,"r11":1,"r12":1,"r13":7,"r14":7,"r15":7,"r16":1,"r17":1,"r18":1}},{"playerId":182,"playerName":"ベネディクト","playerFullName":"ヴィンセント・ベネディクト","category":"NR","rate":2,"score":83.925,"bestSeason":"5期","params":{"spd":9,"tec":9,"pwr":9,"individual":21,"organization":20,"sense":16,"intelligence":21,"r1":1,"r2":1,"r3":1,"r4":1,"r5":1,"r6":1,"r7":1,"r8":1,"r9":1,"r10":1,"r11":1,"r12":1,"r13":7,"r14":7,"r15":7,"r16":1,"r17":1,"r18":1}},{"playerId":429,"playerName":"エルデラ","playerFullName":"アルフ・エルデラ","category":"NR","rate":1,"score":83.897,"bestSeason":"5期","params":{"spd":9,"tec":9,"pwr":9,"individual":22,"organization":21,"sense":23,"intelligence":22,"r1":1,"r2":1,"r3":1,"r4":1,"r5":1,"r6":1,"r7":1,"r8":1,"r9":1,"r10":1,"r11":1,"r12":1,"r13":7,"r14":6,"r15":7,"r16":1,"r17":1,"r18":1}},{"playerId":3048,"playerName":"オルランドーニ","playerFullName":"ジャンルカ・オルランドーニ","category":"NR","rate":5,"score":83.529,"bestSeason":"1期","params":{"spd":9,"tec":9,"pwr":9,"individual":17,"organization":23,"sense":19,"intelligence":22,"r1":1,"r2":1,"r3":1,"r4":1,"r5":1,"r6":1,"r7":1,"r8":1,"r9":1,"r10":2,"r11":2,"r12":2,"r13":7,"r14":7,"r15":6,"r16":1,"r17":1,"r18":2}},{"playerId":603,"playerName":"ファイサル","playerFullName":"ボビー・ファイサル","category":"NR","rate":4,"score":83.222,"bestSeason":"6期","params":{"spd":10,"tec":9,"pwr":9,"individual":20,"organization":20,"sense":17,"intelligence":20,"r1":1,"r2":1,"r3":1,"r4":1,"r5":1,"r6":1,"r7":1,"r8":1,"r9":1,"r10":1,"r11":1,"r12":1,"r13":7,"r14":7,"r15":6,"r16":1,"r17":1,"r18":1}},{"playerId":2651,"playerName":"マニアン","playerFullName":"マルク・マニアン","category":"NR","rate":4,"score":81.785,"bestSeason":"2期","params":{"spd":9,"tec":9,"pwr":9,"individual":21,"organization":19,"sense":20,"intelligence":18,"r1":1,"r2":1,"r3":1,"r4":1,"r5":1,"r6":1,"r7":1,"r8":1,"r9":1,"r10":1,"r11":1,"r12":1,"r13":6,"r14":7,"r15":7,"r16":1,"r17":1,"r18":1}},{"playerId":1006,"playerName":"デル・モンテ","playerFullName":"ダミアン・デル・モンテ","category":"NR","rate":5,"score":80.781,"bestSeason":"9期","params":{"spd":9,"tec":9,"pwr":8,"individual":21,"organization":22,"sense":23,"intelligence":21,"r1":1,"r2":1,"r3":1,"r4":1,"r5":1,"r6":1,"r7":1,"r8":1,"r9":1,"r10":1,"r11":1,"r12":1,"r13":7,"r14":7,"r15":7,"r16":1,"r17":1,"r18":1}},{"playerId":3197,"playerName":"ラモン","playerFullName":"ルメイ・ラモン","category":"SS","rate":7,"score":80.745,"bestSeason":"1期","params":{"spd":8,"tec":9,"pwr":9,"individual":18,"organization":24,"sense":22,"intelligence":23,"r1":1,"r2":1,"r3":1,"r4":1,"r5":1,"r6":1,"r7":1,"r8":1,"r9":1,"r10":1,"r11":1,"r12":1,"r13":7,"r14":7,"r15":7,"r16":1,"r17":1,"r18":1}}]},"2":{"status":"ok","sampleSize":37,"uniquePlayers":10,"confidence":"Low","method":"top_performer_profile_similarity","categoryEffects":{"CC":0.0,"SS":0.0,"CM":0.0,"NR":0.0},"target":{"tec":0.9124,"individual":0.5024,"organization":0.7741,"sense":0.5008,"intelligence":0.7683,"r1":0.2655,"r2":0.1457,"r3":0.5095,"r4":0.2864,"r6":0.7545,"r7":0.5672,"r9":0.9742,"r10":0.6079,"r13":0.1429,"r14":0.1429,"r15":0.1429,"r16":0.2687,"r17":0.4563,"r18":0.5277},"corePattern":{"kind":"high_balanced","primary":"Technique","secondary":"Speed","gaps":[0.0104,0.0752],"level":0.8804,"floor":0.8267},"referencePlayers":[{"playerId":239,"playerName":"カヌー","uses":9,"avgPts":3.7778},{"playerId":471,"playerName":"ローム","uses":1,"avgPts":4.0},{"playerId":489,"playerName":"牛間　隼人","uses":4,"avgPts":3.25},{"playerId":267,"playerName":"G・ネイル","uses":5,"avgPts":2.6},{"playerId":626,"playerName":"イヴァノフ","uses":4,"avgPts":2.0}],"requirements":[{"key":"r6","label":"R6","weight":0.12519},{"key":"r9","label":"R9","weight":0.070732},{"key":"intelligence","label":"Intelligence","weight":0.064648},{"key":"r3","label":"R3","weight":0.057794},{"key":"organization","label":"Organization","weight":0.037191},{"key":"tec","label":"Technique","weight":0.01781}],"top":[{"playerId":239,"playerName":"カヌー","playerFullName":"カヌー","category":"NR","rate":7,"score":86.557,"bestSeason":"7期","params":{"spd":9,"tec":9,"pwr":8,"individual":17,"organization":23,"sense":14,"intelligence":24,"r1":2,"r2":1,"r3":4,"r4":2,"r5":3,"r6":6,"r7":4,"r8":4,"r9":7,"r10":4,"r11":5,"r12":7,"r13":1,"r14":1,"r15":1,"r16":2,"r17":3,"r18":4}},{"playerId":1523,"playerName":"フランシスコ","playerFullName":"フランシスコ","category":"NR","rate":5,"score":75.07,"bestSeason":"3期","params":{"spd":9,"tec":9,"pwr":8,"individual":20,"organization":21,"sense":15,"intelligence":16,"r1":2,"r2":2,"r3":4,"r4":3,"r5":3,"r6":4,"r7":4,"r8":3,"r9":6,"r10":4,"r11":3,"r12":7,"r13":1,"r14":1,"r15":1,"r16":2,"r17":3,"r18":3}},{"playerId":920,"playerName":"デルガド","playerFullName":"ミッシェル・デルガド","category":"SS","rate":7,"score":71.359,"bestSeason":"1期","params":{"spd":9,"tec":9,"pwr":8,"individual":22,"organization":26,"sense":18,"intelligence":20,"r1":1,"r2":1,"r3":2,"r4":2,"r5":2,"r6":3,"r7":2,"r8":4,"r9":7,"r10":4,"r11":5,"r12":7,"r13":1,"r14":1,"r15":1,"r16":1,"r17":3,"r18":5}},{"playerId":3014,"playerName":"リック・ジャービス","playerFullName":"リック・ジャービス","category":"NR","rate":4,"score":71.349,"bestSeason":"3期","params":{"spd":8,"tec":9,"pwr":9,"individual":18,"organization":21,"sense":16,"intelligence":22,"r1":2,"r2":3,"r3":4,"r4":3,"r5":4,"r6":6,"r7":3,"r8":5,"r9":7,"r10":3,"r11":6,"r12":7,"r13":1,"r14":1,"r15":1,"r16":3,"r17":5,"r18":5}},{"playerId":476,"playerName":"リンコン","playerFullName":"リンコン･ナシメント","category":"NR","rate":6,"score":69.647,"bestSeason":"1期","params":{"spd":9,"tec":8,"pwr":9,"individual":23,"organization":17,"sense":22,"intelligence":14,"r1":2,"r2":1,"r3":4,"r4":2,"r5":2,"r6":5,"r7":4,"r8":3,"r9":7,"r10":4,"r11":2,"r12":7,"r13":1,"r14":1,"r15":1,"r16":2,"r17":3,"r18":2}},{"playerId":41,"playerName":"カエキリア","playerFullName":"フェリクス・カエキリア","category":"NR","rate":3,"score":68.936,"bestSeason":"4期","params":{"spd":9,"tec":8,"pwr":9,"individual":15,"organization":17,"sense":13,"intelligence":17,"r1":2,"r2":2,"r3":4,"r4":2,"r5":2,"r6":6,"r7":2,"r8":5,"r9":7,"r10":3,"r11":3,"r12":6,"r13":2,"r14":2,"r15":2,"r16":2,"r17":4,"r18":3}},{"playerId":1960,"playerName":"バルサミコ","playerFullName":"シム・バルサミコ","category":"NR","rate":4,"score":68.904,"bestSeason":"3期","params":{"spd":9,"tec":8,"pwr":9,"individual":18,"organization":20,"sense":22,"intelligence":15,"r1":3,"r2":2,"r3":3,"r4":4,"r5":3,"r6":5,"r7":5,"r8":5,"r9":6,"r10":6,"r11":4,"r12":7,"r13":1,"r14":1,"r15":1,"r16":3,"r17":4,"r18":3}},{"playerId":267,"playerName":"G・ネイル","playerFullName":"ゲイリー・ネイル","category":"NR","rate":7,"score":68.862,"bestSeason":"1期","params":{"spd":9,"tec":9,"pwr":8,"individual":15,"organization":23,"sense":17,"intelligence":22,"r1":1,"r2":1,"r3":1,"r4":2,"r5":2,"r6":2,"r7":4,"r8":5,"r9":6,"r10":5,"r11":6,"r12":7,"r13":1,"r14":1,"r15":1,"r16":2,"r17":3,"r18":5}},{"playerId":1297,"playerName":"セルジーニョ","playerFullName":"セルジ・ドス・カンポス","category":"NR","rate":7,"score":68.181,"bestSeason":"1期","params":{"spd":9,"tec":9,"pwr":8,"individual":16,"organization":23,"sense":19,"intelligence":24,"r1":3,"r2":2,"r3":4,"r4":4,"r5":5,"r6":6,"r7":5,"r8":7,"r9":7,"r10":5,"r11":5,"r12":7,"r13":1,"r14":1,"r15":1,"r16":2,"r17":6,"r18":4}},{"playerId":1940,"playerName":"トインビー","playerFullName":"イーサン・トインビー","category":"NR","rate":4,"score":68.098,"bestSeason":"6期","params":{"spd":8,"tec":7,"pwr":7,"individual":18,"organization":22,"sense":18,"intelligence":21,"r1":1,"r2":2,"r3":3,"r4":2,"r5":3,"r6":5,"r7":3,"r8":3,"r9":7,"r10":3,"r11":3,"r12":7,"r13":1,"r14":1,"r15":1,"r16":2,"r17":3,"r18":3}}]},"3":{"status":"ok","sampleSize":38,"uniquePlayers":10,"confidence":"Low","method":"top_performer_profile_similarity","categoryEffects":{"CC":0.0,"SS":0.0,"CM":0.0,"NR":0.0},"target":{"spd":0.9029,"tec":0.9323,"pwr":0.9051,"individual":0.6849,"organization":0.7137,"sense":0.6903,"r1":0.1953,"r2":0.1603,"r3":0.1953,"r4":0.3876,"r5":0.4224,"r6":0.3876,"r7":0.5889,"r8":0.704,"r10":0.8746,"r12":0.888,"r13":0.3522,"r14":0.3522,"r15":0.3522,"r16":0.2435,"r18":0.9825},"corePattern":{"kind":"high_balanced","primary":"Technique","secondary":"Power","gaps":[0.0272,0.0022],"level":0.9134,"floor":0.9029},"referencePlayers":[{"playerId":230,"playerName":"ロスタ","uses":5,"avgPts":2.6},{"playerId":266,"playerName":"ブルゲラ","uses":1,"avgPts":3.0},{"playerId":457,"playerName":"コルテス","uses":3,"avgPts":2.6667},{"playerId":2567,"playerName":"デニーロ","uses":3,"avgPts":2.6667},{"playerId":639,"playerName":"カンパリ","uses":6,"avgPts":2.3333}],"requirements":[{"key":"r13","label":"R13","weight":0.130349},{"key":"r14","label":"R14","weight":0.130349},{"key":"r15","label":"R15","weight":0.130349},{"key":"sense","label":"Sense","weight":0.077131},{"key":"r12","label":"R12","weight":0.064715},{"key":"r10","label":"R10","weight":0.055079}],"top":[{"playerId":261,"playerName":"アディラ","playerFullName":"ロナルド・アディラ","category":"NR","rate":7,"score":78.96,"bestSeason":"1期","params":{"spd":9,"tec":9,"pwr":9,"individual":20,"organization":21,"sense":18,"intelligence":22,"r1":1,"r2":1,"r3":1,"r4":2,"r5":2,"r6":2,"r7":3,"r8":5,"r9":4,"r10":6,"r11":7,"r12":6,"r13":1,"r14":1,"r15":1,"r16":2,"r17":4,"r18":7}},{"playerId":230,"playerName":"ロスタ","playerFullName":"エンリコ・ロスタ","category":"NR","rate":6,"score":78.166,"bestSeason":"1期","params":{"spd":9,"tec":9,"pwr":9,"individual":20,"organization":21,"sense":23,"intelligence":22,"r1":1,"r2":1,"r3":1,"r4":2,"r5":3,"r6":2,"r7":4,"r8":5,"r9":4,"r10":6,"r11":7,"r12":6,"r13":4,"r14":4,"r15":4,"r16":2,"r17":4,"r18":7}},{"playerId":597,"playerName":"ローズ","playerFullName":"チャド・ローズ","category":"NR","rate":5,"score":74.549,"bestSeason":"3期","params":{"spd":9,"tec":9,"pwr":9,"individual":22,"organization":21,"sense":21,"intelligence":19,"r1":2,"r2":2,"r3":2,"r4":3,"r5":4,"r6":3,"r7":5,"r8":6,"r9":5,"r10":6,"r11":7,"r12":6,"r13":1,"r14":1,"r15":1,"r16":1,"r17":5,"r18":7}},{"playerId":639,"playerName":"カンパリ","playerFullName":"ジェローム・カンパリ","category":"NR","rate":6,"score":74.347,"bestSeason":"1期","params":{"spd":9,"tec":9,"pwr":9,"individual":21,"organization":23,"sense":19,"intelligence":21,"r1":1,"r2":1,"r3":1,"r4":4,"r5":4,"r6":4,"r7":4,"r8":6,"r9":4,"r10":6,"r11":7,"r12":6,"r13":1,"r14":1,"r15":1,"r16":1,"r17":5,"r18":7}},{"playerId":197,"playerName":"マルゲリータ","playerFullName":"ファビオ・マルゲリータ","category":"NR","rate":6,"score":73.941,"bestSeason":"3期","params":{"spd":9,"tec":8,"pwr":9,"individual":24,"organization":18,"sense":19,"intelligence":21,"r1":1,"r2":1,"r3":1,"r4":2,"r5":2,"r6":2,"r7":4,"r8":6,"r9":4,"r10":6,"r11":7,"r12":6,"r13":2,"r14":2,"r15":2,"r16":3,"r17":3,"r18":6}},{"playerId":3196,"playerName":"ラコルデール","playerFullName":"アルベリク・ラコルデール","category":"SS","rate":7,"score":73.513,"bestSeason":"1期","params":{"spd":9,"tec":9,"pwr":9,"individual":19,"organization":25,"sense":17,"intelligence":22,"r1":2,"r2":2,"r3":2,"r4":3,"r5":3,"r6":3,"r7":3,"r8":5,"r9":3,"r10":6,"r11":7,"r12":5,"r13":1,"r14":1,"r15":1,"r16":2,"r17":3,"r18":6}},{"playerId":198,"playerName":"マンチーニ","playerFullName":"パオロ・マンチーニ","category":"NR","rate":6,"score":73.476,"bestSeason":"4期","params":{"spd":9,"tec":9,"pwr":9,"individual":21,"organization":21,"sense":18,"intelligence":22,"r1":1,"r2":1,"r3":1,"r4":4,"r5":2,"r6":2,"r7":6,"r8":3,"r9":4,"r10":7,"r11":7,"r12":5,"r13":2,"r14":2,"r15":2,"r16":2,"r17":2,"r18":6}},{"playerId":512,"playerName":"グレイシー","playerFullName":"チアゴ・グレイシー","category":"NR","rate":6,"score":72.962,"bestSeason":"4期","params":{"spd":9,"tec":9,"pwr":9,"individual":23,"organization":20,"sense":21,"intelligence":20,"r1":2,"r2":1,"r3":2,"r4":2,"r5":2,"r6":3,"r7":5,"r8":6,"r9":6,"r10":6,"r11":7,"r12":6,"r13":1,"r14":1,"r15":1,"r16":1,"r17":5,"r18":7}},{"playerId":2495,"playerName":"ウパペパロ","playerFullName":"バロ・ウパペパロ","category":"SS","rate":7,"score":72.789,"bestSeason":"1期","params":{"spd":9,"tec":9,"pwr":10,"individual":20,"organization":24,"sense":23,"intelligence":24,"r1":2,"r2":2,"r3":2,"r4":3,"r5":3,"r6":3,"r7":4,"r8":6,"r9":4,"r10":5,"r11":7,"r12":5,"r13":1,"r14":1,"r15":1,"r16":2,"r17":4,"r18":7}},{"playerId":447,"playerName":"ワムテル","playerFullName":"ダニエル・ワムテル","category":"NR","rate":5,"score":72.148,"bestSeason":"1期","params":{"spd":9,"tec":8,"pwr":9,"individual":22,"organization":21,"sense":18,"intelligence":23,"r1":1,"r2":1,"r3":1,"r4":2,"r5":2,"r6":2,"r7":4,"r8":4,"r9":4,"r10":6,"r11":7,"r12":6,"r13":1,"r14":1,"r15":1,"r16":2,"r17":3,"r18":6}}]},"4":{"status":"ok","sampleSize":38,"uniquePlayers":9,"confidence":"Low","method":"top_performer_profile_similarity","categoryEffects":{"CC":0.0,"SS":0.0,"CM":0.0282,"NR":-0.0282},"target":{"spd":0.8939,"tec":0.9265,"sense":0.6404,"r1":0.1429,"r3":0.1429,"r5":0.4534,"r6":0.4324,"r7":0.5697,"r8":0.7373,"r12":0.8554,"r13":0.2056,"r14":0.2056,"r15":0.2056,"r16":0.2121,"r17":0.6428,"r18":0.9983},"corePattern":{"kind":"high_balanced","primary":"Power","secondary":"Technique","gaps":[0.0567,0.0327],"level":0.9345,"floor":0.8939},"referencePlayers":[{"playerId":230,"playerName":"ロスタ","uses":1,"avgPts":4.0282},{"playerId":639,"playerName":"カンパリ","uses":12,"avgPts":3.1115},{"playerId":577,"playerName":"コーク","uses":10,"avgPts":2.9282},{"playerId":2500,"playerName":"オランジ","uses":3,"avgPts":2.6948},{"playerId":1028,"playerName":"スポポビッチ","uses":1,"avgPts":2.9718}],"requirements":[{"key":"tec","label":"Technique","weight":0.058118},{"key":"r5","label":"R5","weight":0.051114},{"key":"r17","label":"R17","weight":0.045065},{"key":"r12","label":"R12","weight":0.039604},{"key":"r8","label":"R8","weight":0.034327},{"key":"r13","label":"R13","weight":0.032701}],"top":[{"playerId":639,"playerName":"カンパリ","playerFullName":"ジェローム・カンパリ","category":"NR","rate":6,"score":83.281,"bestSeason":"3期","params":{"spd":9,"tec":9,"pwr":10,"individual":21,"organization":23,"sense":19,"intelligence":21,"r1":1,"r2":1,"r3":1,"r4":4,"r5":4,"r6":4,"r7":4,"r8":6,"r9":4,"r10":6,"r11":7,"r12":6,"r13":1,"r14":1,"r15":1,"r16":1,"r17":5,"r18":7}},{"playerId":597,"playerName":"ローズ","playerFullName":"チャド・ローズ","category":"NR","rate":5,"score":80.385,"bestSeason":"4期","params":{"spd":9,"tec":10,"pwr":9,"individual":22,"organization":21,"sense":21,"intelligence":19,"r1":2,"r2":2,"r3":2,"r4":3,"r5":4,"r6":3,"r7":5,"r8":6,"r9":5,"r10":6,"r11":7,"r12":6,"r13":1,"r14":1,"r15":1,"r16":1,"r17":5,"r18":7}},{"playerId":2495,"playerName":"ウパペパロ","playerFullName":"バロ・ウパペパロ","category":"SS","rate":7,"score":78.843,"bestSeason":"1期","params":{"spd":9,"tec":9,"pwr":10,"individual":20,"organization":24,"sense":23,"intelligence":24,"r1":2,"r2":2,"r3":2,"r4":3,"r5":3,"r6":3,"r7":4,"r8":6,"r9":4,"r10":5,"r11":7,"r12":5,"r13":1,"r14":1,"r15":1,"r16":2,"r17":4,"r18":7}},{"playerId":261,"playerName":"アディラ","playerFullName":"ロナルド・アディラ","category":"NR","rate":7,"score":78.293,"bestSeason":"1期","params":{"spd":9,"tec":9,"pwr":9,"individual":20,"organization":21,"sense":18,"intelligence":22,"r1":1,"r2":1,"r3":1,"r4":2,"r5":2,"r6":2,"r7":3,"r8":5,"r9":4,"r10":6,"r11":7,"r12":6,"r13":1,"r14":1,"r15":1,"r16":2,"r17":4,"r18":7}},{"playerId":481,"playerName":"ペコ","playerFullName":"ミゲール・ペコ","category":"NR","rate":5,"score":76.565,"bestSeason":"1期","params":{"spd":8,"tec":9,"pwr":9,"individual":19,"organization":22,"sense":17,"intelligence":22,"r1":2,"r2":2,"r3":2,"r4":3,"r5":3,"r6":3,"r7":4,"r8":6,"r9":4,"r10":6,"r11":7,"r12":6,"r13":1,"r14":1,"r15":1,"r16":1,"r17":5,"r18":7}},{"playerId":445,"playerName":"モンテッラ","playerFullName":"パウロ・モンテッラ","category":"NR","rate":7,"score":76.371,"bestSeason":"1期","params":{"spd":8,"tec":9,"pwr":9,"individual":24,"organization":18,"sense":21,"intelligence":22,"r1":1,"r2":1,"r3":1,"r4":2,"r5":2,"r6":2,"r7":4,"r8":4,"r9":4,"r10":6,"r11":7,"r12":6,"r13":1,"r14":1,"r15":1,"r16":2,"r17":3,"r18":7}},{"playerId":512,"playerName":"グレイシー","playerFullName":"チアゴ・グレイシー","category":"NR","rate":6,"score":76.359,"bestSeason":"3期","params":{"spd":10,"tec":9,"pwr":10,"individual":23,"organization":20,"sense":21,"intelligence":20,"r1":2,"r2":1,"r3":2,"r4":2,"r5":2,"r6":3,"r7":5,"r8":6,"r9":6,"r10":6,"r11":7,"r12":6,"r13":1,"r14":1,"r15":1,"r16":1,"r17":5,"r18":7}},{"playerId":447,"playerName":"ワムテル","playerFullName":"ダニエル・ワムテル","category":"NR","rate":5,"score":75.624,"bestSeason":"1期","params":{"spd":9,"tec":8,"pwr":9,"individual":22,"organization":21,"sense":18,"intelligence":23,"r1":1,"r2":1,"r3":1,"r4":2,"r5":2,"r6":2,"r7":4,"r8":4,"r9":4,"r10":6,"r11":7,"r12":6,"r13":1,"r14":1,"r15":1,"r16":2,"r17":3,"r18":6}},{"playerId":2742,"playerName":"グアルディバル","playerFullName":"ヨナシュ・グアルディバル","category":"NR","rate":5,"score":75.26,"bestSeason":"1期","params":{"spd":9,"tec":8,"pwr":9,"individual":22,"organization":22,"sense":16,"intelligence":24,"r1":1,"r2":1,"r3":1,"r4":2,"r5":2,"r6":2,"r7":4,"r8":5,"r9":4,"r10":6,"r11":7,"r12":5,"r13":1,"r14":1,"r15":1,"r16":1,"r17":3,"r18":7}},{"playerId":197,"playerName":"マルゲリータ","playerFullName":"ファビオ・マルゲリータ","category":"NR","rate":6,"score":75.195,"bestSeason":"3期","params":{"spd":9,"tec":8,"pwr":9,"individual":24,"organization":18,"sense":19,"intelligence":21,"r1":1,"r2":1,"r3":1,"r4":2,"r5":2,"r6":2,"r7":4,"r8":6,"r9":4,"r10":6,"r11":7,"r12":6,"r13":2,"r14":2,"r15":2,"r16":3,"r17":3,"r18":6}}]},"5":{"status":"insufficient","sampleSize":36,"uniquePlayers":7,"minSamples":30,"minUniquePlayers":8,"top":[],"requirements":[]},"6":{"status":"ok","sampleSize":38,"uniquePlayers":13,"confidence":"Low","method":"top_performer_profile_similarity","categoryEffects":{"CC":0.0,"SS":-0.0133,"CM":0.0,"NR":0.0133},"target":{"spd":0.8539,"pwr":0.9909,"individual":0.7982,"organization":0.7498,"sense":0.5901,"intelligence":0.6871,"r1":0.4266,"r2":0.3562,"r3":0.4266,"r4":0.7254,"r5":0.7782,"r7":0.8376,"r8":0.9869,"r9":0.8571,"r10":0.4286,"r11":0.4879,"r12":0.4351,"r17":0.9869,"r18":0.4174},"corePattern":{"kind":"specialist_plus_support","primary":"Power","secondary":"Technique","gaps":[0.0817,0.0552],"level":0.918,"floor":0.8539},"referencePlayers":[{"playerId":453,"playerName":"ヒューズ","uses":6,"avgPts":2.9867},{"playerId":689,"playerName":"ボイパ","uses":5,"avgPts":2.9867},{"playerId":365,"playerName":"ヨルセン","uses":4,"avgPts":2.7367},{"playerId":462,"playerName":"シュバイツァー","uses":4,"avgPts":2.7367},{"playerId":485,"playerName":"ジャミ・ナバーロ","uses":4,"avgPts":1.9867}],"requirements":[{"key":"individual","label":"Individual","weight":0.112191},{"key":"r7","label":"R7","weight":0.070635},{"key":"r1","label":"R1","weight":0.065735},{"key":"pwr","label":"Power","weight":0.064542},{"key":"r3","label":"R3","weight":0.058216},{"key":"r4","label":"R4","weight":0.037443}],"top":[{"playerId":591,"playerName":"ササ・トーレ","playerFullName":"ササ・トーレ","category":"NR","rate":6,"score":82.801,"bestSeason":"3期","params":{"spd":9,"tec":9,"pwr":10,"individual":24,"organization":22,"sense":15,"intelligence":19,"r1":2,"r2":2,"r3":2,"r4":6,"r5":6,"r6":6,"r7":6,"r8":7,"r9":6,"r10":3,"r11":4,"r12":3,"r13":1,"r14":1,"r15":1,"r16":3,"r17":7,"r18":3}},{"playerId":453,"playerName":"ヒューズ","playerFullName":"ジョージ・ヒューズ","category":"NR","rate":5,"score":82.575,"bestSeason":"6期","params":{"spd":9,"tec":9,"pwr":10,"individual":25,"organization":23,"sense":16,"intelligence":19,"r1":4,"r2":3,"r3":4,"r4":6,"r5":6,"r6":6,"r7":6,"r8":7,"r9":6,"r10":3,"r11":3,"r12":3,"r13":1,"r14":1,"r15":1,"r16":4,"r17":7,"r18":2}},{"playerId":254,"playerName":"ヴィエロ","playerFullName":"クリストフ・ヴィエロ","category":"NR","rate":7,"score":82.207,"bestSeason":"1期","params":{"spd":8,"tec":9,"pwr":10,"individual":24,"organization":22,"sense":18,"intelligence":22,"r1":2,"r2":2,"r3":2,"r4":4,"r5":5,"r6":4,"r7":6,"r8":7,"r9":6,"r10":3,"r11":4,"r12":3,"r13":1,"r14":1,"r15":1,"r16":2,"r17":7,"r18":3}},{"playerId":689,"playerName":"ボイパ","playerFullName":"パトリック・ボイパ","category":"NR","rate":5,"score":81.603,"bestSeason":"5期","params":{"spd":8,"tec":9,"pwr":10,"individual":24,"organization":22,"sense":19,"intelligence":22,"r1":2,"r2":2,"r3":2,"r4":4,"r5":5,"r6":4,"r7":6,"r8":7,"r9":6,"r10":3,"r11":4,"r12":3,"r13":1,"r14":1,"r15":1,"r16":2,"r17":7,"r18":4}},{"playerId":96,"playerName":"ターヒュッツ","playerFullName":"エドガー・ターヒュッツ","category":"NR","rate":5,"score":77.365,"bestSeason":"4期","params":{"spd":9,"tec":8,"pwr":10,"individual":21,"organization":21,"sense":16,"intelligence":19,"r1":3,"r2":1,"r3":2,"r4":6,"r5":5,"r6":6,"r7":7,"r8":7,"r9":6,"r10":3,"r11":3,"r12":3,"r13":2,"r14":1,"r15":2,"r16":2,"r17":7,"r18":3}},{"playerId":1095,"playerName":"バウアー","playerFullName":"ミヒャエル・バウアー","category":"SS","rate":7,"score":77.001,"bestSeason":"1期","params":{"spd":8,"tec":9,"pwr":10,"individual":24,"organization":22,"sense":21,"intelligence":21,"r1":4,"r2":3,"r3":4,"r4":6,"r5":6,"r6":6,"r7":6,"r8":7,"r9":6,"r10":2,"r11":3,"r12":2,"r13":1,"r14":1,"r15":1,"r16":6,"r17":7,"r18":6}},{"playerId":462,"playerName":"シュバイツァー","playerFullName":"ステファン・シュバイツァー","category":"NR","rate":5,"score":76.531,"bestSeason":"4期","params":{"spd":8,"tec":9,"pwr":10,"individual":22,"organization":21,"sense":18,"intelligence":23,"r1":2,"r2":2,"r3":2,"r4":6,"r5":6,"r6":6,"r7":6,"r8":7,"r9":6,"r10":2,"r11":2,"r12":2,"r13":1,"r14":1,"r15":1,"r16":3,"r17":7,"r18":2}},{"playerId":2367,"playerName":"メシェー","playerFullName":"ロラン・メシェー","category":"NR","rate":5,"score":75.84,"bestSeason":"2期","params":{"spd":8,"tec":8,"pwr":9,"individual":21,"organization":23,"sense":18,"intelligence":23,"r1":3,"r2":3,"r3":3,"r4":5,"r5":6,"r6":5,"r7":6,"r8":7,"r9":6,"r10":4,"r11":5,"r12":4,"r13":1,"r14":1,"r15":1,"r16":5,"r17":7,"r18":5}},{"playerId":1046,"playerName":"サンダーソン","playerFullName":"ブライアン・サンダーソン","category":"NR","rate":5,"score":75.614,"bestSeason":"7期","params":{"spd":8,"tec":8,"pwr":9,"individual":19,"organization":22,"sense":20,"intelligence":21,"r1":4,"r2":4,"r3":4,"r4":6,"r5":6,"r6":6,"r7":6,"r8":7,"r9":6,"r10":3,"r11":3,"r12":3,"r13":1,"r14":1,"r15":1,"r16":4,"r17":7,"r18":3}},{"playerId":1701,"playerName":"モウチーニョ","playerFullName":"モウチーニョ","category":"NR","rate":5,"score":74.891,"bestSeason":"2期","params":{"spd":8,"tec":8,"pwr":9,"individual":21,"organization":20,"sense":15,"intelligence":18,"r1":2,"r2":2,"r3":2,"r4":6,"r5":6,"r6":6,"r7":6,"r8":7,"r9":6,"r10":2,"r11":2,"r12":2,"r13":1,"r14":1,"r15":1,"r16":2,"r17":7,"r18":2}}]},"7":{"status":"ok","sampleSize":38,"uniquePlayers":11,"confidence":"Low","method":"top_performer_profile_similarity","categoryEffects":{"CC":0.0,"SS":-0.0656,"CM":0.0,"NR":0.0656},"target":{"tec":0.7538,"individual":0.6534,"organization":0.8414,"sense":0.3978,"intelligence":0.6507,"r1":0.3096,"r2":0.2779,"r3":0.2937,"r4":0.6578,"r5":0.6451,"r7":0.7801,"r9":0.7654,"r10":0.6213,"r11":0.7494,"r12":0.6213,"r13":0.1648,"r14":0.1489,"r15":0.1648,"r17":0.807},"corePattern":{"kind":"specialist_plus_support","primary":"Power","secondary":"Speed","gaps":[0.1008,0.0762],"level":0.8381,"floor":0.7538},"referencePlayers":[{"playerId":253,"playerName":"マテレレ","uses":11,"avgPts":2.9344},{"playerId":591,"playerName":"ササ・トーレ","uses":5,"avgPts":2.5344},{"playerId":96,"playerName":"ターヒュッツ","uses":3,"avgPts":2.6011},{"playerId":692,"playerName":"ミケルセン","uses":5,"avgPts":1.9344},{"playerId":39,"playerName":"カーク","uses":2,"avgPts":1.9344}],"requirements":[{"key":"r11","label":"R11","weight":0.136648},{"key":"r12","label":"R12","weight":0.121287},{"key":"r10","label":"R10","weight":0.106249},{"key":"organization","label":"Organization","weight":0.063327},{"key":"intelligence","label":"Intelligence","weight":0.022629}],"top":[{"playerId":253,"playerName":"マテレレ","playerFullName":"クローデ・マテレレ","category":"NR","rate":7,"score":87.79,"bestSeason":"1期","params":{"spd":8,"tec":7,"pwr":9,"individual":18,"organization":27,"sense":10,"intelligence":20,"r1":2,"r2":2,"r3":2,"r4":4,"r5":4,"r6":4,"r7":5,"r8":7,"r9":5,"r10":5,"r11":6,"r12":5,"r13":1,"r14":1,"r15":1,"r16":3,"r17":5,"r18":4}},{"playerId":1462,"playerName":"バリエ","playerFullName":"アンドレ・バリエ","category":"NR","rate":4,"score":85.145,"bestSeason":"3期","params":{"spd":8,"tec":7,"pwr":9,"individual":20,"organization":23,"sense":18,"intelligence":18,"r1":2,"r2":2,"r3":2,"r4":4,"r5":4,"r6":4,"r7":6,"r8":7,"r9":6,"r10":4,"r11":4,"r12":4,"r13":1,"r14":1,"r15":1,"r16":2,"r17":6,"r18":4}},{"playerId":2557,"playerName":"レイクス","playerFullName":"デミアン・レイクス","category":"NR","rate":5,"score":83.787,"bestSeason":"4期","params":{"spd":7,"tec":8,"pwr":9,"individual":18,"organization":24,"sense":18,"intelligence":23,"r1":2,"r2":2,"r3":2,"r4":4,"r5":4,"r6":4,"r7":6,"r8":7,"r9":6,"r10":4,"r11":6,"r12":4,"r13":1,"r14":1,"r15":1,"r16":2,"r17":7,"r18":6}},{"playerId":541,"playerName":"クセナキス","playerFullName":"ヨハネ・クセナキス","category":"NR","rate":1,"score":83.022,"bestSeason":"2期","params":{"spd":8,"tec":6,"pwr":9,"individual":19,"organization":20,"sense":15,"intelligence":17,"r1":2,"r2":2,"r3":2,"r4":4,"r5":4,"r6":4,"r7":5,"r8":7,"r9":5,"r10":4,"r11":5,"r12":4,"r13":1,"r14":1,"r15":1,"r16":2,"r17":6,"r18":5}},{"playerId":45,"playerName":"カネイラ","playerFullName":"ダニ・カネイラ","category":"NR","rate":1,"score":81.57,"bestSeason":"6期","params":{"spd":7,"tec":8,"pwr":9,"individual":21,"organization":21,"sense":20,"intelligence":20,"r1":2,"r2":2,"r3":2,"r4":4,"r5":5,"r6":5,"r7":5,"r8":7,"r9":6,"r10":4,"r11":5,"r12":4,"r13":1,"r14":1,"r15":1,"r16":3,"r17":6,"r18":4}},{"playerId":351,"playerName":"バミール","playerFullName":"エリック・バミール","category":"NR","rate":3,"score":81.422,"bestSeason":"5期","params":{"spd":7,"tec":8,"pwr":9,"individual":19,"organization":20,"sense":15,"intelligence":21,"r1":2,"r2":2,"r3":2,"r4":5,"r5":5,"r6":5,"r7":6,"r8":7,"r9":6,"r10":5,"r11":5,"r12":5,"r13":1,"r14":1,"r15":1,"r16":4,"r17":7,"r18":4}},{"playerId":1666,"playerName":"ヒカルド","playerFullName":"ヒカルド","category":"NR","rate":4,"score":80.694,"bestSeason":"4期","params":{"spd":7,"tec":8,"pwr":9,"individual":16,"organization":22,"sense":16,"intelligence":22,"r1":2,"r2":2,"r3":2,"r4":3,"r5":3,"r6":3,"r7":5,"r8":7,"r9":5,"r10":4,"r11":5,"r12":4,"r13":1,"r14":1,"r15":1,"r16":2,"r17":6,"r18":4}},{"playerId":2367,"playerName":"メシェー","playerFullName":"ロラン・メシェー","category":"NR","rate":5,"score":80.539,"bestSeason":"1期","params":{"spd":8,"tec":7,"pwr":9,"individual":21,"organization":23,"sense":18,"intelligence":23,"r1":3,"r2":3,"r3":3,"r4":5,"r5":6,"r6":5,"r7":6,"r8":7,"r9":6,"r10":4,"r11":5,"r12":4,"r13":1,"r14":1,"r15":1,"r16":5,"r17":7,"r18":5}},{"playerId":172,"playerName":"ブラグスタッド","playerFullName":"ジョン・ブラグスタッド","category":"NR","rate":3,"score":80.358,"bestSeason":"11期","params":{"spd":8,"tec":8,"pwr":9,"individual":15,"organization":20,"sense":20,"intelligence":15,"r1":2,"r2":2,"r3":2,"r4":4,"r5":6,"r6":4,"r7":5,"r8":7,"r9":5,"r10":4,"r11":5,"r12":4,"r13":1,"r14":1,"r15":1,"r16":3,"r17":7,"r18":5}},{"playerId":240,"playerName":"ロイ・ディーン","playerFullName":"ロイ・ディーン","category":"NR","rate":7,"score":80.145,"bestSeason":"8期","params":{"spd":8,"tec":7,"pwr":9,"individual":19,"organization":21,"sense":21,"intelligence":22,"r1":2,"r2":2,"r3":2,"r4":4,"r5":4,"r6":4,"r7":5,"r8":7,"r9":5,"r10":4,"r11":6,"r12":4,"r13":1,"r14":1,"r15":1,"r16":3,"r17":7,"r18":4}}]},"8":{"status":"ok","sampleSize":38,"uniquePlayers":10,"confidence":"Low","method":"top_performer_profile_similarity","categoryEffects":{"CC":-0.0113,"SS":0.0,"CM":0.0749,"NR":-0.0636},"target":{"spd":0.9447,"tec":0.9938,"pwr":0.8,"sense":0.7831,"intelligence":0.5781,"r1":0.9371,"r2":0.992,"r5":0.8683,"r6":0.7683,"r8":0.3906,"r10":0.1429,"r11":0.1429,"r12":0.1429,"r16":0.9911,"r17":0.6085,"r18":0.1429},"corePattern":{"kind":"double_specialist","primary":"Technique","secondary":"Speed","gaps":[0.0491,0.1447],"level":0.9128,"floor":0.8},"referencePlayers":[{"playerId":570,"playerName":"二宮　和寿","uses":1,"avgPts":5.0636},{"playerId":2735,"playerName":"ファンジオ","uses":3,"avgPts":3.6779},{"playerId":469,"playerName":"ファンジオ","uses":11,"avgPts":3.1545},{"playerId":2038,"playerName":"エフチェンコ","uses":5,"avgPts":3.2636},{"playerId":586,"playerName":"M・ラウンドアップ","uses":4,"avgPts":2.3136}],"requirements":[{"key":"r2","label":"R2","weight":0.17624},{"key":"pwr","label":"Power","weight":0.113158},{"key":"sense","label":"Sense","weight":0.055046},{"key":"r16","label":"R16","weight":0.054998},{"key":"r1","label":"R1","weight":0.049895},{"key":"r17","label":"R17","weight":0.040852}],"top":[{"playerId":570,"playerName":"二宮　和寿","playerFullName":"二宮　和寿","category":"NR","rate":7,"score":88.254,"bestSeason":"1期","params":{"spd":9,"tec":10,"pwr":8,"individual":23,"organization":19,"sense":24,"intelligence":18,"r1":7,"r2":7,"r3":6,"r4":6,"r5":6,"r6":5,"r7":3,"r8":3,"r9":3,"r10":1,"r11":1,"r12":1,"r13":1,"r14":1,"r15":1,"r16":7,"r17":4,"r18":1}},{"playerId":469,"playerName":"ファンジオ","playerFullName":"アンドレス・ファンジオ","category":"NR","rate":6,"score":85.778,"bestSeason":"5期","params":{"spd":10,"tec":10,"pwr":8,"individual":24,"organization":19,"sense":23,"intelligence":15,"r1":6,"r2":7,"r3":7,"r4":6,"r5":6,"r6":6,"r7":3,"r8":3,"r9":3,"r10":1,"r11":1,"r12":1,"r13":1,"r14":1,"r15":1,"r16":7,"r17":5,"r18":1}},{"playerId":2735,"playerName":"ファンジオ","playerFullName":"アンドレス・ファンジオ","category":"CC","rate":7,"score":82.646,"bestSeason":"1期","params":{"spd":10,"tec":10,"pwr":8,"individual":24,"organization":19,"sense":25,"intelligence":16,"r1":6,"r2":7,"r3":7,"r4":6,"r5":7,"r6":6,"r7":2,"r8":2,"r9":2,"r10":1,"r11":1,"r12":1,"r13":1,"r14":1,"r15":1,"r16":7,"r17":5,"r18":1}},{"playerId":2402,"playerName":"イケチュクウ","playerFullName":"オコエ・イケチュクウ","category":"NR","rate":4,"score":81.495,"bestSeason":"1期","params":{"spd":9,"tec":9,"pwr":8,"individual":24,"organization":18,"sense":23,"intelligence":22,"r1":6,"r2":7,"r3":6,"r4":5,"r5":5,"r6":5,"r7":3,"r8":3,"r9":3,"r10":1,"r11":1,"r12":1,"r13":1,"r14":1,"r15":1,"r16":7,"r17":4,"r18":1}},{"playerId":46,"playerName":"カラバッジォ","playerFullName":"アルベルト・カラバッジォ","category":"NR","rate":7,"score":81.415,"bestSeason":"3期","params":{"spd":10,"tec":10,"pwr":8,"individual":18,"organization":18,"sense":26,"intelligence":15,"r1":6,"r2":6,"r3":6,"r4":5,"r5":6,"r6":5,"r7":2,"r8":2,"r9":2,"r10":1,"r11":1,"r12":1,"r13":1,"r14":1,"r15":1,"r16":7,"r17":4,"r18":1}},{"playerId":463,"playerName":"ファーレス","playerFullName":"フランシスコ・ファーレス","category":"NR","rate":5,"score":81.294,"bestSeason":"3期","params":{"spd":9,"tec":9,"pwr":8,"individual":22,"organization":18,"sense":24,"intelligence":17,"r1":7,"r2":7,"r3":6,"r4":5,"r5":5,"r6":5,"r7":2,"r8":2,"r9":2,"r10":1,"r11":1,"r12":1,"r13":1,"r14":1,"r15":1,"r16":6,"r17":4,"r18":1}},{"playerId":2508,"playerName":"コッタ","playerFullName":"ディオ・コッタ","category":"NR","rate":4,"score":81.191,"bestSeason":"1期","params":{"spd":9,"tec":9,"pwr":7,"individual":16,"organization":23,"sense":20,"intelligence":22,"r1":7,"r2":7,"r3":7,"r4":6,"r5":6,"r6":6,"r7":3,"r8":3,"r9":3,"r10":1,"r11":1,"r12":1,"r13":1,"r14":1,"r15":1,"r16":7,"r17":4,"r18":1}},{"playerId":488,"playerName":"ファン・デルリース","playerFullName":"ロメオ・ファン・デルリース","category":"NR","rate":6,"score":80.662,"bestSeason":"1期","params":{"spd":9,"tec":9,"pwr":8,"individual":23,"organization":21,"sense":22,"intelligence":19,"r1":7,"r2":7,"r3":6,"r4":6,"r5":5,"r6":5,"r7":2,"r8":2,"r9":2,"r10":1,"r11":1,"r12":1,"r13":1,"r14":1,"r15":1,"r16":6,"r17":3,"r18":1}},{"playerId":2629,"playerName":"ラファイエット","playerFullName":"テオドール・ラファイエット","category":"NR","rate":4,"score":80.268,"bestSeason":"1期","params":{"spd":9,"tec":9,"pwr":7,"individual":22,"organization":18,"sense":23,"intelligence":22,"r1":6,"r2":7,"r3":7,"r4":5,"r5":5,"r6":6,"r7":3,"r8":3,"r9":3,"r10":1,"r11":1,"r12":1,"r13":1,"r14":1,"r15":1,"r16":7,"r17":4,"r18":1}},{"playerId":620,"playerName":"トンプソン","playerFullName":"ヨハン・ダニエル・トンプソン","category":"NR","rate":7,"score":79.852,"bestSeason":"4期","params":{"spd":8,"tec":9,"pwr":7,"individual":18,"organization":24,"sense":23,"intelligence":19,"r1":6,"r2":7,"r3":6,"r4":6,"r5":7,"r6":6,"r7":3,"r8":3,"r9":3,"r10":1,"r11":1,"r12":1,"r13":1,"r14":1,"r15":1,"r16":7,"r17":4,"r18":1}}]},"9":{"status":"ok","sampleSize":38,"uniquePlayers":14,"confidence":"Low","method":"top_performer_profile_similarity","categoryEffects":{"CC":0.0,"SS":0.0,"CM":0.035,"NR":-0.035},"target":{"spd":0.9454,"tec":0.982,"pwr":0.922,"individual":0.7141,"organization":0.6357,"intelligence":0.6488,"r1":0.9291,"r2":0.7138,"r3":0.9325,"r5":0.7999,"r8":0.5974,"r10":0.265,"r11":0.265,"r12":0.265,"r16":0.7923,"r17":0.7324,"r18":0.2797},"corePattern":{"kind":"high_balanced","primary":"Technique","secondary":"Speed","gaps":[0.0366,0.0233],"level":0.9498,"floor":0.922},"referencePlayers":[{"playerId":215,"playerName":"ラミレス","uses":1,"avgPts":5.035},{"playerId":573,"playerName":"サイコビッチ","uses":5,"avgPts":3.035},{"playerId":39,"playerName":"カーク","uses":4,"avgPts":3.035},{"playerId":2997,"playerName":"ルドルフ","uses":5,"avgPts":2.835},{"playerId":2199,"playerName":"藤堂　征","uses":1,"avgPts":3.035}],"requirements":[{"key":"r1","label":"R1","weight":0.241117},{"key":"r3","label":"R3","weight":0.240763},{"key":"r2","label":"R2","weight":0.127303},{"key":"pwr","label":"Power","weight":0.111517},{"key":"spd","label":"Speed","weight":0.090129},{"key":"tec","label":"Technique","weight":0.029356}],"top":[{"playerId":215,"playerName":"ラミレス","playerFullName":"アンドレス・ラミレス","category":"NR","rate":1,"score":80.386,"bestSeason":"8期","params":{"spd":10,"tec":10,"pwr":10,"individual":21,"organization":21,"sense":21,"intelligence":21,"r1":7,"r2":5,"r3":7,"r4":6,"r5":5,"r6":6,"r7":5,"r8":4,"r9":5,"r10":1,"r11":1,"r12":1,"r13":1,"r14":1,"r15":1,"r16":5,"r17":5,"r18":1}},{"playerId":444,"playerName":"セナ","playerFullName":"セナ","category":"NR","rate":6,"score":79.008,"bestSeason":"4期","params":{"spd":9,"tec":10,"pwr":9,"individual":21,"organization":20,"sense":22,"intelligence":21,"r1":6,"r2":6,"r3":6,"r4":6,"r5":7,"r6":6,"r7":4,"r8":4,"r9":4,"r10":2,"r11":2,"r12":2,"r13":1,"r14":1,"r15":1,"r16":7,"r17":5,"r18":2}},{"playerId":1522,"playerName":"センペ","playerFullName":"ジブリル・センペ","category":"NR","rate":4,"score":77.973,"bestSeason":"4期","params":{"spd":9,"tec":9,"pwr":9,"individual":20,"organization":20,"sense":21,"intelligence":16,"r1":7,"r2":4,"r3":7,"r4":6,"r5":7,"r6":6,"r7":5,"r8":4,"r9":5,"r10":2,"r11":2,"r12":2,"r13":1,"r14":1,"r15":1,"r16":6,"r17":4,"r18":2}},{"playerId":1035,"playerName":"T・フェラー","playerFullName":"テオドール・フェラー","category":"NR","rate":6,"score":76.599,"bestSeason":"4期","params":{"spd":9,"tec":10,"pwr":9,"individual":19,"organization":23,"sense":22,"intelligence":21,"r1":6,"r2":6,"r3":6,"r4":6,"r5":7,"r6":7,"r7":4,"r8":4,"r9":4,"r10":2,"r11":2,"r12":2,"r13":1,"r14":1,"r15":1,"r16":7,"r17":5,"r18":2}},{"playerId":443,"playerName":"ドナルド","playerFullName":"スティリアン・ドナルド","category":"NR","rate":6,"score":75.959,"bestSeason":"8期","params":{"spd":9,"tec":10,"pwr":9,"individual":24,"organization":12,"sense":23,"intelligence":12,"r1":7,"r2":5,"r3":7,"r4":7,"r5":5,"r6":7,"r7":5,"r8":4,"r9":5,"r10":2,"r11":1,"r12":2,"r13":1,"r14":1,"r15":1,"r16":6,"r17":4,"r18":1}},{"playerId":451,"playerName":"ドールマン","playerFullName":"アストン・ドールマン","category":"NR","rate":5,"score":74.278,"bestSeason":"9期","params":{"spd":9,"tec":10,"pwr":9,"individual":24,"organization":12,"sense":21,"intelligence":19,"r1":7,"r2":4,"r3":7,"r4":7,"r5":5,"r6":7,"r7":4,"r8":3,"r9":4,"r10":2,"r11":2,"r12":2,"r13":1,"r14":1,"r15":1,"r16":4,"r17":4,"r18":2}},{"playerId":1995,"playerName":"ドールマン","playerFullName":"アストン・ドールマン","category":"SS","rate":7,"score":74.127,"bestSeason":"1期","params":{"spd":10,"tec":10,"pwr":9,"individual":24,"organization":12,"sense":22,"intelligence":18,"r1":7,"r2":4,"r3":7,"r4":7,"r5":5,"r6":7,"r7":4,"r8":3,"r9":4,"r10":2,"r11":2,"r12":2,"r13":1,"r14":1,"r15":1,"r16":4,"r17":4,"r18":2}},{"playerId":2919,"playerName":"ツァイス","playerFullName":"ニコ・ツァイス","category":"SS","rate":7,"score":73.376,"bestSeason":"1期","params":{"spd":10,"tec":9,"pwr":8,"individual":24,"organization":19,"sense":21,"intelligence":18,"r1":7,"r2":5,"r3":6,"r4":7,"r5":6,"r6":6,"r7":5,"r8":4,"r9":4,"r10":3,"r11":2,"r12":2,"r13":1,"r14":1,"r15":1,"r16":6,"r17":5,"r18":2}},{"playerId":3033,"playerName":"シュターライ","playerFullName":"ダニエル・シュターライ","category":"NR","rate":4,"score":73.075,"bestSeason":"2期","params":{"spd":9,"tec":9,"pwr":8,"individual":22,"organization":20,"sense":22,"intelligence":17,"r1":6,"r2":5,"r3":6,"r4":7,"r5":7,"r6":7,"r7":5,"r8":5,"r9":5,"r10":2,"r11":2,"r12":2,"r13":1,"r14":1,"r15":1,"r16":6,"r17":7,"r18":2}},{"playerId":3003,"playerName":"クルデルスキ","playerFullName":"ダン・クルデルスキ","category":"NR","rate":4,"score":72.818,"bestSeason":"1期","params":{"spd":9,"tec":9,"pwr":8,"individual":23,"organization":21,"sense":23,"intelligence":18,"r1":6,"r2":6,"r3":7,"r4":6,"r5":7,"r6":7,"r7":4,"r8":4,"r9":5,"r10":2,"r11":2,"r12":2,"r13":1,"r14":1,"r15":1,"r16":7,"r17":5,"r18":2}}]},"10":{"status":"ok","sampleSize":38,"uniquePlayers":11,"confidence":"Low","method":"top_performer_profile_similarity","categoryEffects":{"CC":0.0,"SS":0.0,"CM":0.0038,"NR":-0.0038},"target":{"spd":0.9535,"tec":0.8112,"pwr":0.9821,"organization":0.7017,"sense":0.5179,"r1":0.6369,"r2":0.2606,"r3":0.3853,"r4":0.9474,"r5":0.8021,"r7":0.9904,"r8":0.8866,"r9":0.6606,"r10":0.4439,"r11":0.4147,"r12":0.419,"r13":0.1933,"r15":0.1933,"r16":0.6462,"r17":0.8934,"r18":0.3361},"corePattern":{"kind":"double_specialist","primary":"Power","secondary":"Speed","gaps":[0.0286,0.1422],"level":0.9156,"floor":0.8112},"referencePlayers":[{"playerId":237,"playerName":"ハシェック","uses":9,"avgPts":3.1149},{"playerId":96,"playerName":"ターヒュッツ","uses":5,"avgPts":3.2038},{"playerId":244,"playerName":"ライムンド","uses":4,"avgPts":2.5038},{"playerId":636,"playerName":"レイナウド","uses":3,"avgPts":2.3371},{"playerId":598,"playerName":"モラ","uses":4,"avgPts":2.2462}],"requirements":[{"key":"r7","label":"R7","weight":0.197165},{"key":"r8","label":"R8","weight":0.176045},{"key":"pwr","label":"Power","weight":0.111},{"key":"r11","label":"R11","weight":0.106414},{"key":"r17","label":"R17","weight":0.096364},{"key":"r12","label":"R12","weight":0.08816}],"top":[{"playerId":237,"playerName":"ハシェック","playerFullName":"ファべル・ハシェック","category":"NR","rate":6,"score":86.247,"bestSeason":"1期","params":{"spd":10,"tec":8,"pwr":10,"individual":20,"organization":21,"sense":15,"intelligence":20,"r1":5,"r2":2,"r3":3,"r4":7,"r5":6,"r6":5,"r7":7,"r8":6,"r9":4,"r10":3,"r11":3,"r12":3,"r13":1,"r14":1,"r15":1,"r16":6,"r17":6,"r18":2}},{"playerId":96,"playerName":"ターヒュッツ","playerFullName":"エドガー・ターヒュッツ","category":"NR","rate":5,"score":75.851,"bestSeason":"4期","params":{"spd":9,"tec":8,"pwr":10,"individual":21,"organization":21,"sense":16,"intelligence":19,"r1":3,"r2":1,"r3":2,"r4":6,"r5":5,"r6":6,"r7":7,"r8":7,"r9":6,"r10":3,"r11":3,"r12":3,"r13":2,"r14":1,"r15":2,"r16":2,"r17":7,"r18":3}},{"playerId":453,"playerName":"ヒューズ","playerFullName":"ジョージ・ヒューズ","category":"NR","rate":5,"score":73.377,"bestSeason":"6期","params":{"spd":9,"tec":9,"pwr":10,"individual":25,"organization":23,"sense":16,"intelligence":19,"r1":4,"r2":3,"r3":4,"r4":6,"r5":6,"r6":6,"r7":6,"r8":7,"r9":6,"r10":3,"r11":3,"r12":3,"r13":1,"r14":1,"r15":1,"r16":4,"r17":7,"r18":2}},{"playerId":1673,"playerName":"ヒルモア","playerFullName":"クロード・ヒルモア","category":"NR","rate":4,"score":72.873,"bestSeason":"5期","params":{"spd":9,"tec":8,"pwr":9,"individual":19,"organization":20,"sense":20,"intelligence":20,"r1":4,"r2":3,"r3":4,"r4":6,"r5":6,"r6":5,"r7":5,"r8":5,"r9":4,"r10":4,"r11":4,"r12":3,"r13":1,"r14":1,"r15":1,"r16":4,"r17":7,"r18":4}},{"playerId":1538,"playerName":"ナシゴレン","playerFullName":"ガジャ・ナシゴレン","category":"NR","rate":5,"score":72.767,"bestSeason":"3期","params":{"spd":9,"tec":8,"pwr":9,"individual":18,"organization":22,"sense":17,"intelligence":22,"r1":2,"r2":2,"r3":2,"r4":6,"r5":6,"r6":6,"r7":6,"r8":7,"r9":6,"r10":2,"r11":2,"r12":2,"r13":1,"r14":1,"r15":1,"r16":4,"r17":7,"r18":2}},{"playerId":1947,"playerName":"ヴェラルディ","playerFullName":"エミール・ヴェラルディ","category":"NR","rate":5,"score":72.277,"bestSeason":"3期","params":{"spd":9,"tec":8,"pwr":9,"individual":21,"organization":22,"sense":14,"intelligence":18,"r1":6,"r2":3,"r3":3,"r4":6,"r5":5,"r6":5,"r7":6,"r8":7,"r9":6,"r10":5,"r11":4,"r12":4,"r13":1,"r14":1,"r15":1,"r16":3,"r17":7,"r18":4}},{"playerId":591,"playerName":"ササ・トーレ","playerFullName":"ササ・トーレ","category":"NR","rate":6,"score":72.147,"bestSeason":"1期","params":{"spd":9,"tec":8,"pwr":9,"individual":24,"organization":22,"sense":15,"intelligence":19,"r1":2,"r2":2,"r3":2,"r4":6,"r5":6,"r6":6,"r7":6,"r8":7,"r9":6,"r10":3,"r11":4,"r12":3,"r13":1,"r14":1,"r15":1,"r16":3,"r17":7,"r18":3}},{"playerId":449,"playerName":"ランフォード","playerFullName":"フィリップ・ランフォード","category":"NR","rate":6,"score":71.978,"bestSeason":"3期","params":{"spd":9,"tec":8,"pwr":9,"individual":25,"organization":22,"sense":17,"intelligence":21,"r1":4,"r2":3,"r3":4,"r4":6,"r5":7,"r6":6,"r7":5,"r8":6,"r9":5,"r10":2,"r11":2,"r12":2,"r13":1,"r14":1,"r15":1,"r16":5,"r17":7,"r18":2}},{"playerId":544,"playerName":"サファリ","playerFullName":"アリ・サファリ","category":"NR","rate":3,"score":71.405,"bestSeason":"4期","params":{"spd":9,"tec":8,"pwr":9,"individual":19,"organization":20,"sense":15,"intelligence":20,"r1":5,"r2":3,"r3":4,"r4":6,"r5":4,"r6":5,"r7":6,"r8":4,"r9":4,"r10":4,"r11":3,"r12":4,"r13":1,"r14":1,"r15":1,"r16":3,"r17":4,"r18":3}},{"playerId":1701,"playerName":"モウチーニョ","playerFullName":"モウチーニョ","category":"NR","rate":5,"score":71.377,"bestSeason":"3期","params":{"spd":9,"tec":8,"pwr":9,"individual":21,"organization":20,"sense":15,"intelligence":18,"r1":2,"r2":2,"r3":2,"r4":6,"r5":6,"r6":6,"r7":6,"r8":7,"r9":6,"r10":2,"r11":2,"r12":2,"r13":1,"r14":1,"r15":1,"r16":2,"r17":7,"r18":2}}]},"11":{"status":"ok","sampleSize":38,"uniquePlayers":11,"confidence":"Low","method":"top_performer_profile_similarity","categoryEffects":{"CC":0.0,"SS":0.0,"CM":0.0736,"NR":-0.0736},"target":{"spd":0.4507,"tec":0.6474,"organization":0.7974,"sense":0.6234,"intelligence":0.7045,"r1":0.7083,"r3":0.7134,"r4":0.4337,"r5":0.487,"r6":0.4337,"r7":0.2857,"r8":0.2857,"r9":0.2857,"r10":0.1429,"r11":0.1429,"r12":0.1429,"r16":0.8038,"r17":0.4286,"r18":0.1429},"corePattern":{"kind":"single_specialist","primary":"Power","secondary":"Technique","gaps":[0.3272,0.1967],"level":0.6909,"floor":0.4507},"referencePlayers":[{"playerId":1021,"playerName":"ギグー","uses":4,"avgPts":3.5736},{"playerId":2226,"playerName":"オビンフェンナ","uses":5,"avgPts":3.2736},{"playerId":448,"playerName":"グレニテス","uses":6,"avgPts":3.0736},{"playerId":681,"playerName":"デラート","uses":3,"avgPts":3.0736},{"playerId":2168,"playerName":"フェルモ","uses":4,"avgPts":2.8236}],"requirements":[{"key":"organization","label":"Organization","weight":0.064103},{"key":"intelligence","label":"Intelligence","weight":0.046625},{"key":"r16","label":"R16","weight":0.036895}],"top":[{"playerId":1021,"playerName":"ギグー","playerFullName":"フローラン・ギグー","category":"NR","rate":5,"score":86.641,"bestSeason":"1期","params":{"spd":4,"tec":8,"pwr":10,"individual":19,"organization":23,"sense":18,"intelligence":20,"r1":5,"r2":7,"r3":5,"r4":3,"r5":4,"r6":3,"r7":2,"r8":2,"r9":2,"r10":1,"r11":1,"r12":1,"r13":1,"r14":1,"r15":1,"r16":6,"r17":3,"r18":1}},{"playerId":1002,"playerName":"コーラ","playerFullName":"ダン・コーラ","category":"NR","rate":7,"score":86.051,"bestSeason":"1期","params":{"spd":4,"tec":7,"pwr":10,"individual":24,"organization":21,"sense":16,"intelligence":18,"r1":5,"r2":7,"r3":5,"r4":3,"r5":3,"r6":3,"r7":2,"r8":2,"r9":2,"r10":1,"r11":1,"r12":1,"r13":1,"r14":1,"r15":1,"r16":5,"r17":3,"r18":1}},{"playerId":3085,"playerName":"デミデュク","playerFullName":"アルセン・デミデュク","category":"NR","rate":4,"score":84.566,"bestSeason":"7期","params":{"spd":7,"tec":7,"pwr":9,"individual":20,"organization":23,"sense":18,"intelligence":23,"r1":5,"r2":7,"r3":5,"r4":3,"r5":4,"r6":3,"r7":2,"r8":2,"r9":2,"r10":1,"r11":1,"r12":1,"r13":1,"r14":1,"r15":1,"r16":7,"r17":3,"r18":1}},{"playerId":2168,"playerName":"フェルモ","playerFullName":"バレンティン・フェルモ","category":"NR","rate":7,"score":82.743,"bestSeason":"6期","params":{"spd":7,"tec":7,"pwr":10,"individual":24,"organization":23,"sense":25,"intelligence":18,"r1":5,"r2":7,"r3":5,"r4":3,"r5":3,"r6":3,"r7":2,"r8":2,"r9":2,"r10":1,"r11":1,"r12":1,"r13":1,"r14":1,"r15":1,"r16":5,"r17":3,"r18":1}},{"playerId":528,"playerName":"ブルーナ","playerFullName":"ブルーナ・マルク","category":"NR","rate":4,"score":82.134,"bestSeason":"1期","params":{"spd":5,"tec":7,"pwr":9,"individual":21,"organization":23,"sense":17,"intelligence":16,"r1":6,"r2":7,"r3":6,"r4":4,"r5":4,"r6":4,"r7":2,"r8":2,"r9":2,"r10":1,"r11":1,"r12":1,"r13":1,"r14":1,"r15":1,"r16":5,"r17":3,"r18":1}},{"playerId":2821,"playerName":"アルファルファ","playerFullName":"ギョスタ・アルファルファ","category":"NR","rate":4,"score":81.699,"bestSeason":"6期","params":{"spd":5,"tec":7,"pwr":9,"individual":22,"organization":23,"sense":16,"intelligence":23,"r1":5,"r2":7,"r3":5,"r4":4,"r5":4,"r6":4,"r7":3,"r8":3,"r9":3,"r10":1,"r11":1,"r12":1,"r13":1,"r14":1,"r15":1,"r16":6,"r17":4,"r18":1}},{"playerId":460,"playerName":"クロイツ","playerFullName":"ミハイル・クロイツ","category":"NR","rate":6,"score":81.092,"bestSeason":"3期","params":{"spd":9,"tec":8,"pwr":10,"individual":22,"organization":23,"sense":20,"intelligence":21,"r1":6,"r2":7,"r3":6,"r4":3,"r5":3,"r6":3,"r7":2,"r8":2,"r9":2,"r10":1,"r11":1,"r12":1,"r13":1,"r14":1,"r15":1,"r16":5,"r17":3,"r18":1}},{"playerId":2031,"playerName":"コーラ","playerFullName":"ダン・コーラ","category":"SS","rate":7,"score":79.349,"bestSeason":"1期","params":{"spd":7,"tec":9,"pwr":10,"individual":24,"organization":22,"sense":19,"intelligence":20,"r1":4,"r2":7,"r3":4,"r4":3,"r5":3,"r6":3,"r7":2,"r8":2,"r9":2,"r10":1,"r11":1,"r12":1,"r13":1,"r14":1,"r15":1,"r16":5,"r17":3,"r18":1}},{"playerId":448,"playerName":"グレニテス","playerFullName":"エルナンド・グレニテス","category":"NR","rate":6,"score":78.917,"bestSeason":"7期","params":{"spd":7,"tec":7,"pwr":8,"individual":20,"organization":23,"sense":17,"intelligence":20,"r1":6,"r2":7,"r3":6,"r4":3,"r5":3,"r6":3,"r7":2,"r8":2,"r9":2,"r10":1,"r11":1,"r12":1,"r13":1,"r14":1,"r15":1,"r16":6,"r17":3,"r18":1}},{"playerId":286,"playerName":"レプスキ","playerFullName":"トーマス・レプスキ","category":"NR","rate":2,"score":76.982,"bestSeason":"3期","params":{"spd":6,"tec":5,"pwr":9,"individual":17,"organization":20,"sense":20,"intelligence":18,"r1":6,"r2":7,"r3":6,"r4":4,"r5":4,"r6":4,"r7":3,"r8":3,"r9":3,"r10":1,"r11":1,"r12":1,"r13":1,"r14":1,"r15":1,"r16":5,"r17":4,"r18":1}}]}}}